datasette_upgrade/__init__.py
datasette_upgrade-0.1a0.dist-info/LICENSE
datasette_upgrade-0.1a0.dist-info/METADATA
datasette_upgrade-0.1a0.dist-info/WHEEL
datasette_upgrade-0.1a0.dist-info/entry_points.txt
datasette_upgrade-0.1a0.dist-info/top_level.txt
datasette_upgrade-0.1a0.dist-info/RECORD
