Metadata-Version: 2.1
Name: datasette-upgrade
Version: 0.1a0
Summary: Upgrade Datasette instance configuration to handle new features
Author: Simon Willison
License: Apache-2.0
Project-URL: Homepage, https://github.com/datasette/datasette-upgrade
Project-URL: Changelog, https://github.com/datasette/datasette-upgrade/releases
Project-URL: Issues, https://github.com/datasette/datasette-upgrade/issues
Project-URL: CI, https://github.com/datasette/datasette-upgrade/actions
Classifier: Framework :: Datasette
Classifier: License :: OSI Approved :: Apache Software License
Requires-Python: >=3.8
License-File: LICENSE
Requires-Dist: datasette
Provides-Extra: test
Requires-Dist: pytest ; extra == 'test'
Requires-Dist: pytest-asyncio ; extra == 'test'
